greenbutton/__init__.py
greenbutton/greenbutton.py
greenbutton/sample_data/SDGEElectricIntervalDataFeb12011toJan312012.xml
jendobson.greenbutton-0.0.1.dist-info/LICENSE
jendobson.greenbutton-0.0.1.dist-info/METADATA
jendobson.greenbutton-0.0.1.dist-info/WHEEL
jendobson.greenbutton-0.0.1.dist-info/top_level.txt
jendobson.greenbutton-0.0.1.dist-info/RECORD
