Metadata-Version: 2.1
Name: jendobson.greenbutton
Version: 0.0.1
Summary: Python tools to explore GreenButton data.
Home-page: https://github.com/JenDobson/greenbutton
Author: Jen Dobson
Author-email: jendobson@gmail.com
License: UNKNOWN
Keywords: greenbutton energy
Platform: UNKNOWN
Classifier: Programming Language :: Python :: 3
Classifier: License :: OSI Approved :: MIT License
Classifier: Operating System :: OS Independent
Classifier: Development Status :: 3 - Alpha
Requires-Python: >=3.7
Requires-Dist: xmlschema
Requires-Dist: pandas
Requires-Dist: matplotlib
